ALP4.py
alp4lib-1.0.3.dist-info/licenses/LICENSE
alp4lib-1.0.3.dist-info/METADATA
alp4lib-1.0.3.dist-info/WHEEL
alp4lib-1.0.3.dist-info/top_level.txt
alp4lib-1.0.3.dist-info/RECORD
