Metadata-Version: 2.4
Name: ALP4lib
Version: 1.0.3
Summary: A module to control Vialux DMDs based on ALP4.X API.It uses the .ddl files provided by Vialux.
Home-page: https://github.com/wavefronthsaping/ALP4lib
Author: Sebastien Popoff
Author-email: sebastien.popoff@espci.fr
License: MIT
Keywords: DMD Vialux
Classifier: Programming Language :: Python :: 2
Classifier: Programming Language :: Python :: 3
Classifier: Development Status :: 3 - Alpha
Classifier: Intended Audience :: Education
Classifier: Topic :: Scientific/Engineering
Classifier: License :: OSI Approved :: MIT License
License-File: LICENSE
Requires-Dist: numpy
Requires-Dist: matplotlib
Requires-Dist: scipy
Requires-Dist: numba
Requires-Dist: joblib
Dynamic: author
Dynamic: author-email
Dynamic: classifier
Dynamic: description
Dynamic: home-page
Dynamic: keywords
Dynamic: license
Dynamic: license-file
Dynamic: requires-dist
Dynamic: summary
